LICENSE
README.md
pyproject.toml
setup.py
abcd_rf_fit/__init__.py
abcd_rf_fit/abcd_rf_fit.py
abcd_rf_fit/fraction_fit.py
abcd_rf_fit/plot.py
abcd_rf_fit/resonators.py
abcd_rf_fit/synthetic_signal.py
abcd_rf_fit/utils.py
abcd_rf_fit.egg-info/PKG-INFO
abcd_rf_fit.egg-info/SOURCES.txt
abcd_rf_fit.egg-info/dependency_links.txt
abcd_rf_fit.egg-info/requires.txt
abcd_rf_fit.egg-info/top_level.txt