Metadata-Version: 2.1
Name: abcd-rf-fit
Version: 0.1.3
Summary: Rational function fit library
Home-page: https://github.com/UlysseREGLADE/abcd_rf_fit
Author: Ulysse REGLADE
Author-email: ulysse.reglade@yahoo.fr
License: License :: OSI Approved :: BSD License
Platform: UNKNOWN
Classifier: Development Status :: 3 - Alpha
Classifier: Intended Audience :: Science/Research
Classifier: License :: OSI Approved :: BSD License
Classifier: Programming Language :: Python :: 3
Classifier: Programming Language :: Python :: 3.10
Classifier: Programming Language :: Python :: 3.11
Classifier: Programming Language :: Python :: 3.12
License-File: LICENSE
